synse/__init__.py
synse/client.py
synse/errors.py
synse/models.py
synse/utils.py
synse-1.0.1.dist-info/LICENSE
synse-1.0.1.dist-info/METADATA
synse-1.0.1.dist-info/WHEEL
synse-1.0.1.dist-info/top_level.txt
synse-1.0.1.dist-info/RECORD
