Metadata-Version: 2.1
Name: synse
Version: 1.0.1
Summary: The official Python client for interacting with the Synse Server API.
Home-page: https://github.com/vapor-ware/synse-client-python
Author: Vapor IO
Author-email: erick@vapor.io
License: GNU General Public License v3.0
Platform: UNKNOWN
Classifier: Intended Audience :: Developers
Classifier: Natural Language :: English
Classifier: Programming Language :: Python
Classifier: Programming Language :: Python :: 3
Classifier: Programming Language :: Python :: 3.6
Requires-Python: >=3.6
Requires-Dist: aiodns
Requires-Dist: aiohttp
Requires-Dist: cchardet
Requires-Dist: iso8601
Requires-Dist: multidict
